{
  "Instance": "Grave_Protocol_1",
  "OrderPosition": 1,
    "SpawnPositions": [
        {
            "X": 5,
            "Y": 81,
            "Z": 0
        },
        {
            "X": -5,
            "Y": 81,
            "Z": 0
        },
        {
            "X": 0,
            "Y": 81,
            "Z": 5
        },
        {
            "X": 0,
            "Y": 81,
            "Z": -5
        }
    ],
    "ShopPosition": {
        "X": 0,
        "Y": 80,
        "Z": 0
    },
  "Multipliers": {
    "ShopHealthMultiplier": 1.12,
    "TowerHealthMultiplier": 1.08,
    "TowerAttackMultiplier": 1.08,
    "EnemyHealthMultiplier": 1.15,
    "EnemyAttackMultiplier": 1.1
  },
    "PathBlocks": [
        "Rock_Chalk"
    ]
}

